[
  {
    "number": 21,
    "nickname": "Red_Skull\r\nИсточник: https://www.samp-sektor.ru/forum/10-17615-144"
  },
  {
    "number": 44,
    "nickname": "Mr_IIaJIuBo\r\nИсточник: https://www.samp-sektor.ru/forum/10-17615-144"
  },
  {
    "number": 67,
    "nickname": "Echpochmak\r\nИсточник: https://www.samp-sektor.ru/forum/10-17615-145"
  },
  {
    "number": 7,
    "nickname": "Wolverine\r\nИсточник: https://www.samp-sektor.ru/forum/10-17615-145"
  },
  {
    "number": 15,
    "nickname": "Lockdown_\r\nИсточник: https://www.samp-sektor.ru/forum/10-17615-145"
  },
  {
    "number": 30,
    "nickname": "Kaznokrad\r\nИсточник: https://www.samp-sektor.ru/forum/10-17615-145"
  },
  {
    "number": 69,
    "nickname": "BOJlK\r\nИсточник: https://www.samp-sektor.ru/forum/10-17615-145"
  },
  {
    "number": 58,
    "nickname": "Any_Yash\r\nИсточник: https://www.samp-sektor.ru/forum/10-17615-145"
  },
  {
    "number": 85,
    "nickname": "Dima_MMO\r\nИсточник: https://www.samp-sektor.ru/forum/10-17615-145"
  },
  {
    "number": 38,
    "nickname": "nemesida\r\nИсточник: https://www.samp-sektor.ru/forum/10-17615-145"
  },
  {
    "number": 33,
    "nickname": "Guts\r\nИсточник: https://www.samp-sektor.ru/forum/10-17615-145"
  },
  {
    "number": 49,
    "nickname": "Azrael\r\nИсточник: https://www.samp-sektor.ru/forum/10-17615-145"
  },
  {
    "number": 65,
    "nickname": "Mr_IIaJIuBo\r\nИсточник: https://www.samp-sektor.ru/forum/10-17615-145"
  }
]